mds/__init__.py
medical_data_structure-0.0.0.dist-info/LICENSE
medical_data_structure-0.0.0.dist-info/METADATA
medical_data_structure-0.0.0.dist-info/WHEEL
medical_data_structure-0.0.0.dist-info/top_level.txt
medical_data_structure-0.0.0.dist-info/RECORD
