Metadata-Version: 2.1
Name: medical-data-structure
Version: 0.0.0
Summary: Example package for medical data structure utils (Cooming Soon)
Author-email: Maria Monzon <mariamonzondeveloper@gmail.com>
License-File: LICENSE
